plotly_upset/__init__.py
plotly_upset/plotting.py
plotly_upset/util.py
plotly_upset_hd-0.0.2.dist-info/LICENSE
plotly_upset_hd-0.0.2.dist-info/METADATA
plotly_upset_hd-0.0.2.dist-info/WHEEL
plotly_upset_hd-0.0.2.dist-info/top_level.txt
plotly_upset_hd-0.0.2.dist-info/RECORD
