Metadata-Version: 2.2
Name: plotly_upset_hd
Version: 0.0.2
Summary: UpSet intersection visualization utility for Plotly (Python-only) - Fork of plotly-upset by Hasan Shahrier
Home-page: https://github.com/pranjalpruthi/plotly-upset-hd
Author: Pranjal Pruthi
Author-email: pranjalpruthi@gmail.com
Maintainer: Pranjal Pruthi
Maintainer-email: pranjalpruthi@gmail.com
License: MIT
Classifier: Development Status :: 4 - Beta
Classifier: Intended Audience :: Science/Research
Classifier: License :: OSI Approved :: MIT License
Classifier: Programming Language :: Python :: 3
Classifier: Topic :: Scientific/Engineering :: Visualization
License-File: LICENSE
Requires-Dist: plotly>=5.5.0
Requires-Dist: numpy>=1.21.6
Requires-Dist: pandas>=1.3.5
Requires-Dist: kaleido>=0.2.1
Dynamic: author
Dynamic: author-email
Dynamic: classifier
Dynamic: description
Dynamic: description-content-type
Dynamic: home-page
Dynamic: license
Dynamic: maintainer
Dynamic: maintainer-email
Dynamic: requires-dist
Dynamic: summary
